alirpa_pack.py
alirpa_pack-3.0.3.dist-info/METADATA
alirpa_pack-3.0.3.dist-info/WHEEL
alirpa_pack-3.0.3.dist-info/top_level.txt
alirpa_pack-3.0.3.dist-info/RECORD
