Metadata-Version: 2.1
Name: alirpa-pack
Version: 3.0.3
Summary: use to package python modules for rpa
Home-page: UNKNOWN
Author: AlibabaCloudRPA
Author-email: alibaba_cloud_rpa@alibaba-inc.com
License: UNKNOWN
Keywords: rpa
Platform: UNKNOWN
